ar/__init__.py
ar/ardrive.py
ar/arweave_lib.py
ar/block.py
ar/bundle.py
ar/chunk.py
ar/manifest.py
ar/multipeer.py
ar/peer.py
ar/stream.py
ar/transaction.py
ar/wallet.py
ar/utils/__init__.py
ar/utils/ans104_signers.py
ar/utils/deep_hash.py
ar/utils/file_io.py
ar/utils/merkle.py
ar/utils/serialization.py
ar/utils/transaction_uploader.py
bundlr/__init__.py
bundlr/loader.py
bundlr/node.py
ritual_pyarweave-0.1.2.dist-info/METADATA
ritual_pyarweave-0.1.2.dist-info/WHEEL
ritual_pyarweave-0.1.2.dist-info/RECORD
